plccng-0.0.5.dist-info/METADATA
plccng-0.0.5.dist-info/WHEEL
plccng-0.0.5.dist-info/entry_points.txt
plccng/__init__.py
plccng/load_spec/__init__.py
plccng/load_spec/errors.py
plccng/load_spec/load_rough_spec/__init__.py
plccng/load_spec/load_rough_spec/load_rough_spec.py
plccng/load_spec/load_rough_spec/load_rough_spec_test.py
plccng/load_spec/load_rough_spec/parse_blocks.py
plccng/load_spec/load_rough_spec/parse_blocks_test.py
plccng/load_spec/load_rough_spec/parse_dividers.py
plccng/load_spec/load_rough_spec/parse_dividers_test.py
plccng/load_spec/load_rough_spec/parse_includes.py
plccng/load_spec/load_rough_spec/parse_includes_test.py
plccng/load_spec/load_rough_spec/parse_lines.py
plccng/load_spec/load_rough_spec/parse_lines_test.py
plccng/load_spec/load_rough_spec/parse_rough.py
plccng/load_spec/load_rough_spec/parse_rough_test.py
plccng/load_spec/load_rough_spec/process_includes_test.py
plccng/load_spec/load_rough_spec/split_rough_spec.py
plccng/load_spec/load_rough_spec/split_rough_spec_test.py
plccng/load_spec/load_rough_spec/validate_rough_spec.py
plccng/load_spec/load_rough_spec/validate_rough_spec_test.py
plccng/load_spec/parse_spec/__init__.py
plccng/load_spec/parse_spec/parse_lexical_spec.py
plccng/load_spec/parse_spec/parse_lexical_spec_test.py
plccng/load_spec/parse_spec/parse_semantic_spec/__init__.py
plccng/load_spec/parse_spec/parse_semantic_spec/parse_code_fragments.py
plccng/load_spec/parse_spec/parse_semantic_spec/parse_code_fragments_test.py
plccng/load_spec/parse_spec/parse_semantic_spec/parse_semantic_spec.py
plccng/load_spec/parse_spec/parse_semantic_spec/parse_semantic_spec_test.py
plccng/load_spec/parse_spec/parse_semantic_spec/parse_target_locator.py
plccng/load_spec/parse_spec/parse_semantic_spec/parse_target_locator_test.py
plccng/load_spec/parse_spec/parse_syntactic_spec/__init__.py
plccng/load_spec/parse_spec/parse_syntactic_spec/parse_syntactic_spec.py
plccng/load_spec/parse_spec/parse_syntactic_spec/parse_syntactic_spec_test.py
plccng/load_spec/structs.py
plccng/load_spec/validate_spec/__init__.py
plccng-0.0.5.dist-info/RECORD
