Metadata-Version: 2.1
Name: plccng
Version: 0.0.5
Summary: Programming Languages Compiler Compiler
Author-Email: PLCC Community <https://discord.gg/EVtNSxS9E2>
License: GPL-3.0-or-later
Requires-Python: >=3.10
